TCLIService/TCLIService.py
TCLIService/__init__.py
TCLIService/constants.py
TCLIService/ttypes.py
pyhive/__init__.py
pyhive/common.py
pyhive/exc.py
pyhive/hive.py
pyhive/presto.py
pyhive/sasl_compat.py
pyhive/sqlalchemy_hive.py
pyhive/sqlalchemy_presto.py
pyhive/sqlalchemy_sparksql.py
pyhive/sqlalchemy_trino.py
pyhive/trino.py
acryl_PyHive-0.6.16.dist-info/LICENSE
acryl_PyHive-0.6.16.dist-info/METADATA
acryl_PyHive-0.6.16.dist-info/WHEEL
acryl_PyHive-0.6.16.dist-info/entry_points.txt
acryl_PyHive-0.6.16.dist-info/top_level.txt
acryl_PyHive-0.6.16.dist-info/RECORD
