Metadata-Version: 2.1
Name: acryl-PyHive
Version: 0.6.16
Summary: Python interface to Hive
Home-page: https://github.com/acryldata/PyHive
Author: Acryl Data
Author-email: datahub@acryl.io
License: Apache License, Version 2.0
Classifier: Intended Audience :: Developers
Classifier: License :: OSI Approved :: Apache Software License
Classifier: Operating System :: OS Independent
Classifier: Topic :: Database :: Front-Ends
License-File: LICENSE
Requires-Dist: future
Requires-Dist: python-dateutil
Provides-Extra: hive
Requires-Dist: sasl3 >=0.2.11 ; extra == 'hive'
Requires-Dist: thrift >=0.10.0 ; extra == 'hive'
Requires-Dist: thrift-sasl >=0.1.0 ; extra == 'hive'
Provides-Extra: hive-pure-sasl
Requires-Dist: pure-sasl >=0.6.2 ; extra == 'hive-pure-sasl'
Requires-Dist: thrift >=0.10.0 ; extra == 'hive-pure-sasl'
Requires-Dist: thrift-sasl >=0.1.0 ; extra == 'hive-pure-sasl'
Provides-Extra: kerberos
Requires-Dist: requests-kerberos >=0.12.0 ; extra == 'kerberos'
Provides-Extra: presto
Requires-Dist: requests >=1.0.0 ; extra == 'presto'
Provides-Extra: sqlalchemy
Requires-Dist: sqlalchemy <1.4.0,>=1.3.0 ; extra == 'sqlalchemy'
Provides-Extra: trino
Requires-Dist: requests >=1.0.0 ; extra == 'trino'
